gzw_xhs_bailian_mcp_server/__init__.py
gzw_xhs_bailian_mcp_server/server.py
gzw_xhs_bailian_mcp_server-0.1.0.dist-info/WHEEL
gzw_xhs_bailian_mcp_server-0.1.0.dist-info/entry_points.txt
gzw_xhs_bailian_mcp_server-0.1.0.dist-info/METADATA
gzw_xhs_bailian_mcp_server-0.1.0.dist-info/RECORD
