Metadata-Version: 2.3
Name: gzw-xhs-bailian-mcp-server
Version: 0.1.0
Summary: Add your description here
Requires-Dist: bs4>=0.0.2
Requires-Dist: dashscope>=1.24.6
Requires-Dist: dotenv>=0.9.9
Requires-Dist: httpx>=0.28.1
Requires-Dist: mcp[cli]>=1.16.0
Requires-Python: >=3.10
